Workbook

Sheet Resumen
A1: Ferretería Robledo, S.L. - Historias de usuario (v2.0)
A2: Generado a partir de los 3 TXT de docs/AnalistaRequisitos (08/10/2026). Detalle y trazabilidad en requisitos-ferreteria-robledo-v2.docx. Sustituye a la v1 sin modificarla.
A4: Historias por prioridad y fase
A5: Prioridad | B5: F1 | C5: F1* | D5: F2 | E5: F2* | F5: Aparcado | G5: Total
A6: Must | B6: =COUNTIFS('Historias de usuario'!$G$2:$G$46,$A6,'Historias de usuario'!$H$2:$H$46,SUBSTITUTE(B$5,"*","~*")) | C6: =COUNTIFS('Historias de usuario'!$G$2:$G$46,$A6,'Historias de usuario'!$H$2:$H$46,SUBSTITUTE(C$5,"*","~*")) | D6: =COUNTIFS('Historias de usuario'!$G$2:$G$46,$A6,'Historias de usuario'!$H$2:$H$46,SUBSTITUTE(D$5,"*","~*")) | E6: =COUNTIFS('Historias de usuario'!$G$2:$G$46,$A6,'Historias de usuario'!$H$2:$H$46,SUBSTITUTE(E$5,"*","~*")) | F6: =COUNTIFS('Historias de usuario'!$G$2:$G$46,$A6,'Historias de usuario'!$H$2:$H$46,SUBSTITUTE(F$5,"*","~*")) | G6: =SUM(B6:F6)
A7: Should | B7: =COUNTIFS('Historias de usuario'!$G$2:$G$46,$A7,'Historias de usuario'!$H$2:$H$46,SUBSTITUTE(B$5,"*","~*")) | C7: =COUNTIFS('Historias de usuario'!$G$2:$G$46,$A7,'Historias de usuario'!$H$2:$H$46,SUBSTITUTE(C$5,"*","~*")) | D7: =COUNTIFS('Historias de usuario'!$G$2:$G$46,$A7,'Historias de usuario'!$H$2:$H$46,SUBSTITUTE(D$5,"*","~*")) | E7: =COUNTIFS('Historias de usuario'!$G$2:$G$46,$A7,'Historias de usuario'!$H$2:$H$46,SUBSTITUTE(E$5,"*","~*")) | F7: =COUNTIFS('Historias de usuario'!$G$2:$G$46,$A7,'Historias de usuario'!$H$2:$H$46,SUBSTITUTE(F$5,"*","~*")) | G7: =SUM(B7:F7)
A8: Could | B8: =COUNTIFS('Historias de usuario'!$G$2:$G$46,$A8,'Historias de usuario'!$H$2:$H$46,SUBSTITUTE(B$5,"*","~*")) | C8: =COUNTIFS('Historias de usuario'!$G$2:$G$46,$A8,'Historias de usuario'!$H$2:$H$46,SUBSTITUTE(C$5,"*","~*")) | D8: =COUNTIFS('Historias de usuario'!$G$2:$G$46,$A8,'Historias de usuario'!$H$2:$H$46,SUBSTITUTE(D$5,"*","~*")) | E8: =COUNTIFS('Historias de usuario'!$G$2:$G$46,$A8,'Historias de usuario'!$H$2:$H$46,SUBSTITUTE(E$5,"*","~*")) | F8: =COUNTIFS('Historias de usuario'!$G$2:$G$46,$A8,'Historias de usuario'!$H$2:$H$46,SUBSTITUTE(F$5,"*","~*")) | G8: =SUM(B8:F8)
A9: Won't | B9: =COUNTIFS('Historias de usuario'!$G$2:$G$46,$A9,'Historias de usuario'!$H$2:$H$46,SUBSTITUTE(B$5,"*","~*")) | C9: =COUNTIFS('Historias de usuario'!$G$2:$G$46,$A9,'Historias de usuario'!$H$2:$H$46,SUBSTITUTE(C$5,"*","~*")) | D9: =COUNTIFS('Historias de usuario'!$G$2:$G$46,$A9,'Historias de usuario'!$H$2:$H$46,SUBSTITUTE(D$5,"*","~*")) | E9: =COUNTIFS('Historias de usuario'!$G$2:$G$46,$A9,'Historias de usuario'!$H$2:$H$46,SUBSTITUTE(E$5,"*","~*")) | F9: =COUNTIFS('Historias de usuario'!$G$2:$G$46,$A9,'Historias de usuario'!$H$2:$H$46,SUBSTITUTE(F$5,"*","~*")) | G9: =SUM(B9:F9)
A10: Total | B10: =SUM(B6:B9) | C10: =SUM(C6:C9) | D10: =SUM(D6:D9) | E10: =SUM(E6:E9) | F10: =SUM(F6:F9) | G10: =SUM(G6:G9)
A12: Historias por épica
A13: Épica | B13: Historias | C13: Must
A14: A. Catálogo y stock | B14: =COUNTIF('Historias de usuario'!$B$2:$B$46,A14) | C14: =COUNTIFS('Historias de usuario'!$B$2:$B$46,A14,'Historias de usuario'!$G$2:$G$46,"Must")
A15: B. Venta en mostrador | B15: =COUNTIF('Historias de usuario'!$B$2:$B$46,A15) | C15: =COUNTIFS('Historias de usuario'!$B$2:$B$46,A15,'Historias de usuario'!$G$2:$G$46,"Must")
A16: C. Facturación | B16: =COUNTIF('Historias de usuario'!$B$2:$B$46,A16) | C16: =COUNTIFS('Historias de usuario'!$B$2:$B$46,A16,'Historias de usuario'!$G$2:$G$46,"Must")
A17: D. Compras y proveedores | B17: =COUNTIF('Historias de usuario'!$B$2:$B$46,A17) | C17: =COUNTIFS('Historias de usuario'!$B$2:$B$46,A17,'Historias de usuario'!$G$2:$G$46,"Must")
A18: E. Usuarios y permisos | B18: =COUNTIF('Historias de usuario'!$B$2:$B$46,A18) | C18: =COUNTIFS('Historias de usuario'!$B$2:$B$46,A18,'Historias de usuario'!$G$2:$G$46,"Must")
A19: F. Informes e integraciones | B19: =COUNTIF('Historias de usuario'!$B$2:$B$46,A19) | C19: =COUNTIFS('Historias de usuario'!$B$2:$B$46,A19,'Historias de usuario'!$G$2:$G$46,"Must")
A20: G. Operación y continuidad | B20: =COUNTIF('Historias de usuario'!$B$2:$B$46,A20) | C20: =COUNTIFS('Historias de usuario'!$B$2:$B$46,A20,'Historias de usuario'!$G$2:$G$46,"Must")
A21: H. Aparcadas | B21: =COUNTIF('Historias de usuario'!$B$2:$B$46,A21) | C21: =COUNTIFS('Historias de usuario'!$B$2:$B$46,A21,'Historias de usuario'!$G$2:$G$46,"Must")
A22: Total | B22: =SUM(B14:B21) | C22: =SUM(C14:C21)
A24: Requisitos
A25: Tipo | B25: Must | C25: Should | D25: Could | E25: Won't | F25: Total
A26: Funcionales (RF) | B26: =COUNTIFS(Requisitos!$A$2:$A$55,"RF-*",Requisitos!$D$2:$D$55,"Must") | C26: =COUNTIFS(Requisitos!$A$2:$A$55,"RF-*",Requisitos!$D$2:$D$55,"Should") | D26: =COUNTIFS(Requisitos!$A$2:$A$55,"RF-*",Requisitos!$D$2:$D$55,"Could") | E26: =COUNTIFS(Requisitos!$A$2:$A$55,"RF-*",Requisitos!$D$2:$D$55,"Won't") | F26: =SUM(B26:E26)
A27: No funcionales (RNF) | B27: =COUNTIFS(Requisitos!$A$2:$A$55,"RNF-*",Requisitos!$D$2:$D$55,"Must") | C27: =COUNTIFS(Requisitos!$A$2:$A$55,"RNF-*",Requisitos!$D$2:$D$55,"Should") | D27: =COUNTIFS(Requisitos!$A$2:$A$55,"RNF-*",Requisitos!$D$2:$D$55,"Could") | E27: =COUNTIFS(Requisitos!$A$2:$A$55,"RNF-*",Requisitos!$D$2:$D$55,"Won't") | F27: =SUM(B27:E27)
A29: Preguntas abiertas pendientes | B29: =COUNTIF('Preguntas abiertas'!$F$2:$F$27,"Pendiente")
A31: Notas
A32: F1 y F2 son las fases acordadas en el correo del 07/10/2026; F1* y F2* son propuestas del analista (F1* se puede aplazar si el calendario aprieta) y deben validarse con el cliente.
A33: Las historias HU-23 (vender sin stock) y HU-31 (pedidos a proveedor) dependen de decisiones pendientes del cliente (Q-01, Q-02).
A34: HU-41 (cobrar sin internet) y HU-26 (Verifactu) requieren análisis de arquitectura antes de planificarse (Q-04, Q-05, Q-06).
A35: El estado de desarrollo (hoja Historias de usuario, última columna) se puede actualizar con la lista desplegable.

Sheet Historias de usuario
A1: ID | B1: Épica | C1: Como (rol) | D1: Quiero | E1: Para | F1: Criterios de aceptación (Dado / Cuando / Entonces) | G1: Prioridad (MoSCoW) | H1: Fase | I1: Requisitos asociados | J1: Dependencias / preguntas abiertas | K1: Estado vs. proyecto actual | L1: Estado de desarrollo
A2: HU-01 | B2: A. Catálogo y stock | C2: Responsable de almacén y compras (Javier) | D2: Quiero gestionar el catálogo de productos con referencia, descripción, familia, proveedor, precios, stock mínimo y observaciones | E2: Para tener un único catálogo fiable en lugar de dos Excel | F2: 1. Dado un producto nuevo, cuando indico referencia, descripción, familia, proveedor, precio de compra y PVP sin IVA, entonces queda guardado y aparece en el catálogo. 2. Dado que ya existe la referencia FR-0001, cuando intento crear otra con la misma referencia, entonces el sistema la rechaza con un mensaje claro. 3. Dado un precio o stock negativo o no numérico, cuando intento guardar, entonces el sistema lo rechaza indicando el campo. | G2: Must | H2: F1 | I2: RF-03 | J2: — | K2: Nuevo | L2: Pendiente
A3: HU-02 | B3: A. Catálogo y stock | C3: Responsable de almacén y compras (Javier) | D3: Quiero importar el listado de productos desde Excel/CSV | E3: Para no volver a teclear los productos de la nave y de la tienda | F3: 1. Dado el listado con las 9 columnas del formato actual, cuando lo importo, entonces se crean los productos y se informa de cuántos se han creado y cuáles se han rechazado y por qué. 2. Dado un importe con coma decimal (98,40) y tildes (Tornillería), cuando importo, entonces se interpretan correctamente. 3. Dado que importo dos veces el mismo fichero, cuando termina la segunda, entonces no hay referencias duplicadas. | G3: Must | H3: F1 | I3: RF-04 | J3: Q-09 | K3: Nuevo | L3: Pendiente
A4: HU-03 | B4: A. Catálogo y stock | C4: Responsable de almacén y compras (Javier) | D4: Quiero asociar uno o varios códigos de barras a cada producto | E4: Para poder vender leyendo el código con la pistola | F4: 1. Dado un producto sin código, cuando le asigno un código de barras, entonces queda guardado. 2. Dado un código ya asignado a otro producto, cuando intento asignarlo, entonces el sistema lo rechaza indicando a qué producto pertenece. 3. Dado un producto con varios códigos (unidad y caja), cuando lo busco por cualquiera de ellos, entonces se localiza el mismo producto. | G4: Must | H4: F1 | I4: RF-05 | J4: Q-10, Q-11 | K4: Nuevo | L4: Pendiente
A5: HU-04 | B5: A. Catálogo y stock | C5: Responsable de almacén y compras (Javier) | D5: Quiero ver y mantener el stock de cada producto por ubicación (nave y tienda) | E5: Para saber qué hay realmente en cada sitio | F5: 1. Dado un producto con 7 unidades en la nave y 2 en la tienda, cuando consulto la nave, entonces veo 7; y cuando consulto la tienda, veo 2. 2. Dado un usuario sin permiso de almacén, cuando intenta modificar el stock, entonces el sistema lo impide. | G5: Must | H5: F1 | I5: RF-01 | J5: — | K5: Nuevo | L5: Pendiente
A6: HU-05 | B6: A. Catálogo y stock | C6: Dirección (Marisa) | D6: Quiero ver en una sola pantalla el stock de todas las ubicaciones con total y desglose | E6: Para tener una visión global sin abrir dos Excel | F6: 1. Dado un producto con stock en ambas ubicaciones, cuando abro la vista global, entonces veo el total y el desglose por ubicación. 2. Dado el filtro por familia o por referencia, cuando lo aplico, entonces solo se muestran los productos que coinciden. | G6: Must | H6: F1 | I6: RF-02 | J6: — | K6: Nuevo | L6: Pendiente
A7: HU-06 | B7: A. Catálogo y stock | C7: Responsable de almacén y compras (Javier) | D7: Quiero registrar entradas de mercancía y ajustes manuales de stock con motivo | E7: Para mantener el stock correcto cuando llega género o hay diferencias | F7: 1. Dado una entrada de 20 unidades en la nave, cuando la registro, entonces el stock de la nave aumenta en 20 y queda un movimiento con usuario, fecha y motivo. 2. Dado un ajuste sin motivo, cuando intento guardarlo, entonces el sistema lo rechaza. | G7: Must | H7: F1 | I7: RF-07 | J7: — | K7: Nuevo | L7: Pendiente
A8: HU-07 | B8: A. Catálogo y stock | C8: Personal de mostrador | D8: Quiero que cada venta descuente el stock de la ubicación donde se realiza | E8: Para no tener que actualizar el stock a mano | F8: 1. Dado una venta de 2 unidades en la tienda, cuando se cobra, entonces el stock de la tienda baja en 2 y el de la nave no cambia. 2. Dado una devolución de 1 unidad, cuando se registra, entonces el stock de esa ubicación sube en 1. | G8: Must | H8: F1 | I8: RF-06 | J8: Q-01 | K8: Nuevo | L8: Pendiente
A9: HU-08 | B9: A. Catálogo y stock | C9: Responsable de almacén y compras (Javier) | D9: Quiero traspasar unidades entre la nave y la tienda | E9: Para reflejar el movimiento de género entre ubicaciones | F9: 1. Dado un traspaso de 5 unidades de la nave a la tienda, cuando lo confirmo, entonces la nave baja en 5 y la tienda sube en 5 en una única operación. 2. Dado que la nave tiene menos unidades de las traspasadas, cuando intento confirmar, entonces el sistema lo rechaza. | G9: Should | H9: F1* | I9: RF-08 | J9: — | K9: Nuevo | L9: Pendiente
A10: HU-09 | B10: A. Catálogo y stock | C10: Responsable de almacén y compras (Javier) | D10: Quiero recibir un aviso en la pantalla principal de los productos por debajo del stock mínimo | E10: Para pedir a tiempo sin revisar el Excel | F10: 1. Dado el listado actual, cuando abro la pantalla principal, entonces aparecen al menos FR-0024, FR-0033 y FR-0053 como productos bajo mínimo. 2. Dado un producto cuyo stock iguala su mínimo, cuando se evalúa el aviso, entonces no se marca (criterio a confirmar en Q-13). 3. Dado un producto descatalogado, cuando se evalúa el aviso, entonces no aparece. | G10: Should | H10: F1* | I10: RF-09, RF-10 | J10: Q-13 | K10: Nuevo | L10: Pendiente
A11: HU-10 | B11: A. Catálogo y stock | C11: Responsable de almacén y compras (Javier) | D11: Quiero marcar un producto como descatalogado / no reponer | E11: Para evitar avisos y pedidos de productos que ya no se compran | F11: 1. Dado FR-0080 marcado como descatalogado, cuando se generan avisos o propuestas de pedido, entonces no aparece. 2. Dado un producto descatalogado con stock, cuando se vende, entonces sigue pudiendo venderse hasta agotarlo. | G11: Should | H11: F1* | I11: RF-10 | J11: — | K11: Nuevo | L11: Pendiente
A12: HU-11 | B12: A. Catálogo y stock | C12: Personal de mostrador | D12: Quiero ver la foto del producto en su ficha y al venderlo | E12: Para distinguir referencias parecidas siendo nuevo en el mostrador | F12: 1. Dado un producto con foto, cuando lo abro o lo añado a la venta, entonces veo la foto. 2. Dado un fichero que no es imagen o que supera el tamaño permitido, cuando intento subirlo, entonces el sistema lo rechaza. | G12: Should | H12: F1* | I12: RF-12 | J12: — | K12: Nuevo | L12: Pendiente
... A46: HU-45 | B46: B. Venta en mostrador | C46: Responsable de facturación y cobros (Lucía) | D46: Quiero importar el listado de clientes (NIF, régimen de recargo de equivalencia y descuentos por familia) desde Excel/CSV | E46: Para no teclear a mano los clientes habituales ni los autónomos en recargo de equivalencia | F46: 1. Dado un listado con NIF, régimen (RE sí/no) y descuento por familia, cuando lo importo, entonces se crean los clientes y se informa de cuántos se han creado y cuáles se han rechazado y por qué. 2. Dado un cliente marcado en recargo de equivalencia, cuando lo consulto, entonces figura con ese régimen y sus descuentos por familia. 3. Dado que importo dos veces el mismo listado, cuando termina la segunda, entonces no hay clientes duplicados por NIF. | G46: Should | H46: F1* | I46: RF-43, RF-21 | J46: Q-08 | K46: Nuevo | L46: Pendiente

Sheet Requisitos
A1: ID | B1: Grupo | C1: Requisito | D1: Prioridad (MoSCoW) | E1: Fase | F1: Fuente | G1: Tipo | H1: Verificación | I1: Estado vs. proyecto actual
A2: RF-01 | B2: Catálogo y stock | C2: El sistema debe mantener el stock de cada producto por separado en la nave y en la tienda. | D2: Must | E2: F1 | F2: COR; PET | G2: Explícito | H2: Una venta en la tienda no cambia el stock de la nave. | I2: Nuevo
A3: RF-02 | B3: Catálogo y stock | C3: El sistema debe mostrar en una sola pantalla el stock de ambas ubicaciones, con total y desglose. | D3: Must | E3: F1 | F3: PET | G3: Explícito | H3: Pantalla con columnas Nave, Tienda y Total por producto. | I3: Nuevo
A4: RF-03 | B4: Catálogo y stock | C4: El sistema debe gestionar un catálogo con referencia, descripción, familia, proveedor, precio de compra, PVP sin IVA, stock, stock mínimo y observaciones. | D4: Must | E4: F1 | F4: LIS | G4: Explícito | H4: Alta, edición y consulta de un producto con todos los campos. | I4: Nuevo
A5: RF-04 | B5: Catálogo y stock | C5: El sistema debe importar el listado de productos desde Excel/CSV (formato español: coma decimal, tildes) sin duplicar referencias. | D5: Must | E5: F1 | F5: COR; LIS | G5: Supuesto | H5: Importar las 39 líneas de LIS dos veces deja 39 productos. | I5: Nuevo
A6: RF-05 | B6: Catálogo y stock | C6: El sistema debe asociar uno o varios códigos de barras a cada producto. | D6: Must | E6: F1 | F6: COR; LIS (sin columna) | G6: Supuesto | H6: Un código no puede estar en dos productos. | I6: Nuevo
A7: RF-06 | B7: Catálogo y stock | C7: El sistema debe descontar el stock vendido de la ubicación de la venta y reponerlo en las devoluciones. | D7: Must | E7: F1 | F7: COR | G7: Supuesto | H7: Vender 2 uds. reduce el stock en 2; devolverlas lo restaura. | I7: Nuevo
A8: RF-07 | B8: Catálogo y stock | C8: El sistema debe registrar entradas de mercancía y ajustes manuales de stock por ubicación con motivo, usuario y fecha. | D8: Must | E8: F1 | F8: COR; LIS | G8: Supuesto | H8: Todo cambio de stock deja un movimiento consultable. | I8: Nuevo
A9: RF-08 | B9: Catálogo y stock | C9: El sistema debe traspasar unidades de un producto entre nave y tienda. | D9: Should | E9: F1* | F9: PET | G9: Supuesto | H9: Un traspaso resta en origen y suma en destino en una sola operación. | I9: Nuevo
A10: RF-09 | B10: Catálogo y stock | C10: El sistema debe avisar en la pantalla principal de los productos con stock inferior al mínimo (correo opcional, Q-13). | D10: Should | E10: F1* | F10: PET (Javier) | G10: Explícito | H10: Con los datos de LIS aparecen FR-0024, FR-0033 y FR-0053. | I10: Nuevo
A11: RF-10 | B11: Catálogo y stock | C11: El sistema debe marcar productos como descatalogados y excluirlos de avisos y pedidos. | D11: Should | E11: F1* | F11: LIS (FR-0080) | G11: Supuesto | H11: FR-0080 marcado no genera aviso ni propuesta de pedido. | I11: Nuevo
A12: RF-11 | B12: Catálogo y stock | C12: El sistema debe listar los productos sin ventas en los últimos seis meses. | D12: Could | E12: F2* | F12: PET | G12: Explícito | H12: Listado filtrable por ubicación y familia. | I12: Nuevo
... A55: RNF-13 | B55: No funcional | C55: Restricción de proceso: presupuesto no indicado ("primero dime qué me vais a hacer"); la propuesta de alcance y plazos de F1 se entrega antes del 17/10/2026. | D55: Must | E55: Proceso | F55: PET; COR | G55: Explícito | H55: Propuesta entregada en plazo. | I55: Nuevo

Sheet Preguntas abiertas
A1: ID | B1: Descripción | C1: Fuentes implicadas | D1: Pregunta para el cliente | E1: Impacto | F1: Estado
A2: Q-01 | B2: CONFLICTO. Vender sin stock: Marisa sí (el camión llega por la tarde), Javier no (líos con clientes). | C2: PET; COR | D2: ¿Se permite? Si sí, ¿para todos o con autorización de Marisa/Lucía? ¿Se acepta stock negativo? | E2: Crítico (RF-23) | F2: Pendiente
A3: Q-02 | B3: CONFLICTO. Pedidos a proveedor: Javier automáticos al bajar del mínimo; Marisa revisar siempre. | C3: PET; COR | D3: ¿Aceptáis propuesta automática con aprobación manual? ¿Quién aprueba y cómo se envía? | E3: Alto (RF-31) | F3: Pendiente
A4: Q-03 | B4: HUECO. No se cuenta qué pasó en 2023. | C4: PET; COR | D4: ¿Qué ocurrió (fallo de disco, borrado, ransomware, error humano)? ¿Cuánta pérdida de datos es tolerable? | E4: Alto (RNF-03) | F4: Pendiente
A5: Q-04 | B5: HUECO. Dónde se instala (servidor en la nave, nube, un PC por sede), equipos y puestos de cobro. | C5: COR; PET | D5: ¿Qué equipos y conexión hay? ¿Servidor local o nube? | E5: Crítico | F5: Pendiente
A6: Q-05 | B6: AMBIGÜEDAD. "Que funcione sin internet": qué y cuánto tiempo. | C6: PET | D6: ¿Basta con cobrar en mostrador? ¿Hasta cuántas horas? | E6: Crítico (RNF-01) | F6: Pendiente
A7: Q-06 | B7: HUECO. Verifactu: modalidad, certificado, series, declaración responsable. | C7: PET; COR | D7: ¿Qué modalidad prefiere el gestor? ¿Hay certificado digital? | E7: Crítico | F7: Pendiente
A8: Q-07 | B8: HUECO. Documento fiscal del mostrador. | C8: COR; PET | D8: ¿Todo ticket es factura simplificada? ¿Cuándo pasa a factura completa? | E8: Alto (RF-28) | F8: Pendiente
A9: Q-08 | B9: HUECO. Falta el listado de clientes en RE y con descuento. | C9: COR; PET | D9: ¿Podéis enviar clientes con NIF, régimen y descuento por familia antes del 17/10? | E9: Alto (RF-21, 22, 27, 43) | F9: Pendiente
A10: Q-09 | B10: HUECO. Sin Excel de la tienda; listado de la nave posiblemente parcial. | C10: LIS; COR | D10: ¿Podéis enviar el Excel de la tienda y el listado completo? | E10: Alto (RF-04) | F10: Pendiente
A11: Q-10 | B11: HUECO. Sin códigos de barras en LIS. | C11: LIS; COR | D11: ¿Los productos traen EAN? ¿Quién etiqueta los que no? ¿Cajas y unidades tienen códigos distintos? | E11: Alto (RF-05, 15) | F11: Pendiente
A12: Q-11 | B12: AMBIGÜEDAD. Cajas/packs/rollos (11 de 39). | C12: LIS | D12: ¿Se venden también por unidad suelta? | E12: Medio | F12: Pendiente
... A27: Q-26 | B27: INTERNA. El proyecto actual es otra aplicación. | C27: docs/analisis-diseño.md | D27: Equipo: ¿proyecto nuevo o dentro de este repositorio? | E27: Alto | F27: Pendiente

Sheet Cambios v1 a v2
A1: Cambio | B1: Motivo
A2: Fases separadas en F1 (acordada) y F1* (propuesta aplazable); idem F2 / F2*. | B2: Distinguir lo que el cliente acordó de lo que propone el analista y dar un colchón de calendario (R-03).
A3: Columna Verificación en cada requisito. | B3: Hacerlos comprobables (criterio de calidad).
A4: RF-32 (albarán manual) baja de Must a Should. | B4: La entrada de stock ya la cubre RF-07; los albaranes están en F2 según COR.
A5: Nuevo RF-43 (importar listado de clientes). | B5: COR pide el listado de clientes en RE y no había requisito que lo cargara.
A6: RF-42 retirado y movido a fuera de alcance. | B6: Era una pregunta, no una necesidad; Q-21 asume que no se sustituye.
A7: RNF-05 fusionado con RF-17. | B7: Duplicado.
A8: RNF-13 marcado como restricción de proceso. | B8: No es un requisito del sistema.
A9: Regla de precedencia COR > PET y matriz de trazabilidad simplificada por fuente. | B9: Resolver discrepancias de forma explícita; sin referencias a historias de usuario que cambien con la numeración.
A10: Se añade valor del stock a PVP (13.400,80 €) y la lista de épicas incorpora E0 (encaje y spike). | B10: Datos verificados sobre LIS y riesgos R-01/R-02/Q-26.
A11: Historias: HU-32 baja a Should (por RF-32); HU-45 nueva (por RF-43); fases renombradas a F1/F1*/F2/F2*; HU-17 deja de citar RNF-05. | B11: Mantener las historias alineadas con los requisitos v2.
